{
  "entityType" : "WIDGET_TYPE",
  "entity" : {
    "fqn" : "time_series_black_2",
    "name" : "custom time series",
    "deprecated" : false,
    "image" : "tb-image;/api/images/system/chart.svg",
    "description" : "Displays changes to time series data over time—for example, temperature or humidity readings.\nLabels, leyenda letras negras",
    "descriptor" : {
      "type" : "timeseries",
      "sizeX" : 8,
      "sizeY" : 5,
      "resources" : [ ],
      "templateHtml" : "<tb-time-series-chart-widget \n    [ctx]=\"ctx\">\n</tb-time-series-chart-widget>",
      "templateCss" : "",
      "controllerScript" : "self.onInit = function() {\n    self.ctx.$scope.timeSeriesChartWidget.onInit();\n};\n\nself.onDataUpdated = function() {\n    self.ctx.$scope.timeSeriesChartWidget.onDataUpdated();\n}\n\nself.onLatestDataUpdated = function() {\n    self.ctx.$scope.timeSeriesChartWidget.onLatestDataUpdated();\n}\n\nself.typeParameters = function() {\n    return {\n        previewWidth: '80%',\n        embedTitlePanel: true,\n        embedActionsPanel: true,\n        hasAdditionalLatestDataKeys: true,\n        supportsUnitConversion: true,\n        dataKeySettingsFunction: TbTimeSeriesChart.dataKeySettings(),\n        defaultDataKeysFunction: function() {\n            return [{ name: 'temperature', label: 'Temperature', type: 'timeseries', units: '°C', decimals: 0 }];\n        }\n    };\n}\n",
      "settingsForm" : [ ],
      "dataKeySettingsForm" : [ ],
      "latestDataKeySettingsForm" : [ ],
      "settingsDirective" : "tb-time-series-chart-widget-settings",
      "dataKeySettingsDirective" : "tb-time-series-chart-key-settings",
      "latestDataKeySettingsDirective" : "",
      "hasBasicMode" : true,
      "basicModeDirective" : "tb-time-series-chart-basic-config",
      "defaultConfig" : "{\"datasources\":[{\"type\":\"function\",\"name\":\"function\",\"dataKeys\":[{\"name\":\"f(x)\",\"type\":\"function\",\"label\":\"Second\",\"color\":\"#FFC107\",\"settings\":{\"yAxisId\":\"default\",\"showInLegend\":true,\"dataHiddenByDefault\":false,\"type\":\"line\",\"lineSettings\":{\"showLine\":true,\"step\":false,\"stepType\":\"start\",\"smooth\":false,\"lineType\":\"solid\",\"lineWidth\":2,\"showPoints\":true,\"showPointLabel\":false,\"pointLabelPosition\":\"top\",\"pointLabelFont\":{\"family\":\"Roboto\",\"size\":11,\"sizeUnit\":\"px\",\"style\":\"normal\",\"weight\":\"400\",\"lineHeight\":\"1\"},\"pointLabelColor\":\"rgba(0, 0, 0, 0.76)\",\"enablePointLabelBackground\":false,\"pointLabelBackground\":\"rgba(255,255,255,0.56)\",\"pointShape\":\"circle\",\"pointSize\":4,\"fillAreaSettings\":{\"type\":\"none\",\"opacity\":0.4,\"gradient\":{\"start\":100,\"end\":0}}},\"barSettings\":{\"showBorder\":false,\"borderWidth\":2,\"borderRadius\":0,\"showLabel\":false,\"labelPosition\":\"top\",\"labelFont\":{\"family\":\"Roboto\",\"size\":11,\"sizeUnit\":\"px\",\"style\":\"normal\",\"weight\":\"400\",\"lineHeight\":\"1\"},\"labelColor\":\"rgba(0, 0, 0, 0.76)\",\"enableLabelBackground\":false,\"labelBackground\":\"rgba(255,255,255,0.56)\",\"backgroundSettings\":{\"type\":\"none\",\"opacity\":0.4,\"gradient\":{\"start\":100,\"end\":0}}},\"tooltipValueFormatter\":null,\"comparisonSettings\":{\"showValuesForComparison\":false,\"comparisonValuesLabel\":\"\",\"color\":\"\"}},\"_hash\":0.5534217244004682,\"funcBody\":\"var value = prevValue + Math.random() * 100 - 50;\\nvar multiplier = Math.pow(10, 2 || 0);\\nvar value = Math.round(value * multiplier) / multiplier;\\nif (value < -1000) {\\n\\tvalue = -1000;\\n} else if (value > 1000) {\\n\\tvalue = 1000;\\n}\\nreturn value;\",\"aggregationType\":null,\"units\":null,\"decimals\":null,\"usePostProcessing\":null,\"postFuncBody\":null}],\"alarmFilterConfig\":{\"statusList\":[\"ACTIVE\"]},\"latestDataKeys\":null},{\"type\":\"function\",\"name\":\"function\",\"dataKeys\":[{\"name\":\"f(x)\",\"type\":\"function\",\"label\":\"Sin\",\"color\":\"#4caf50\",\"settings\":{\"yAxisId\":\"default\",\"showInLegend\":true,\"dataHiddenByDefault\":false,\"type\":\"line\",\"lineSettings\":{\"showLine\":true,\"step\":false,\"stepType\":\"start\",\"smooth\":false,\"lineType\":\"solid\",\"lineWidth\":2,\"showPoints\":true,\"showPointLabel\":false,\"pointLabelPosition\":\"top\",\"pointLabelFont\":{\"family\":\"Roboto\",\"size\":11,\"sizeUnit\":\"px\",\"style\":\"normal\",\"weight\":\"400\",\"lineHeight\":\"1\"},\"pointLabelColor\":\"rgba(0, 0, 0, 0.76)\",\"enablePointLabelBackground\":false,\"pointLabelBackground\":\"rgba(255,255,255,0.56)\",\"pointShape\":\"circle\",\"pointSize\":4,\"fillAreaSettings\":{\"type\":\"none\",\"opacity\":0.4,\"gradient\":{\"start\":100,\"end\":0}}},\"barSettings\":{\"showBorder\":false,\"borderWidth\":2,\"borderRadius\":0,\"showLabel\":false,\"labelPosition\":\"top\",\"labelFont\":{\"family\":\"Roboto\",\"size\":11,\"sizeUnit\":\"px\",\"style\":\"normal\",\"weight\":\"400\",\"lineHeight\":\"1\"},\"labelColor\":\"rgba(0, 0, 0, 0.76)\",\"enableLabelBackground\":false,\"labelBackground\":\"rgba(255,255,255,0.56)\",\"backgroundSettings\":{\"type\":\"none\",\"opacity\":0.4,\"gradient\":{\"start\":100,\"end\":0}}},\"tooltipValueFormatter\":null,\"comparisonSettings\":{\"showValuesForComparison\":false,\"comparisonValuesLabel\":\"\",\"color\":\"\"}},\"_hash\":0.8495038571323346,\"funcBody\":\"return Math.round(1000*Math.sin(time/5000));\",\"aggregationType\":null,\"units\":null,\"decimals\":null,\"usePostProcessing\":null,\"postFuncBody\":null}],\"alarmFilterConfig\":{\"statusList\":[\"ACTIVE\"]},\"latestDataKeys\":[]}],\"timewindow\":{\"hideAggregation\":false,\"hideAggInterval\":false,\"hideTimezone\":false,\"selectedTab\":0,\"realtime\":{\"realtimeType\":0,\"interval\":5000,\"timewindowMs\":600000,\"quickInterval\":\"CURRENT_DAY\",\"hideInterval\":false,\"hideLastInterval\":false,\"hideQuickInterval\":false},\"history\":{\"historyType\":0,\"interval\":1000,\"timewindowMs\":60000,\"fixedTimewindow\":null,\"quickInterval\":\"CURRENT_DAY\",\"hideInterval\":false,\"hideLastInterval\":false,\"hideFixedInterval\":false,\"hideQuickInterval\":false},\"aggregation\":{\"type\":\"AVG\",\"limit\":25000},\"timezone\":null},\"showTitle\":true,\"backgroundColor\":\"rgba(0, 0, 0, 0)\",\"color\":\"rgba(0, 0, 0, 0.87)\",\"padding\":\"0px\",\"settings\":{\"comparisonEnabled\":false,\"timeForComparison\":\"previousInterval\",\"comparisonCustomIntervalValue\":7200000,\"comparisonXAxis\":{\"show\":true,\"label\":\"\",\"labelFont\":{\"family\":\"Roboto\",\"size\":12,\"sizeUnit\":\"px\",\"style\":\"normal\",\"weight\":\"600\",\"lineHeight\":\"1\"},\"labelColor\":\"rgba(0, 0, 0, 0.54)\",\"position\":\"top\",\"showTickLabels\":true,\"tickLabelFont\":{\"family\":\"Roboto\",\"size\":10,\"sizeUnit\":\"px\",\"style\":\"normal\",\"weight\":\"400\",\"lineHeight\":\"1\"},\"tickLabelColor\":\"rgba(0, 0, 0, 0.54)\",\"ticksFormat\":{},\"showTicks\":true,\"ticksColor\":\"rgba(0, 0, 0, 0.54)\",\"showLine\":true,\"lineColor\":\"rgba(0, 0, 0, 0.54)\",\"showSplitLines\":true,\"splitLinesColor\":\"rgba(0, 0, 0, 0.12)\"},\"yAxes\":{\"default\":{\"units\":null,\"decimals\":0,\"show\":true,\"label\":\"\",\"labelFont\":{\"family\":\"Roboto\",\"size\":12,\"sizeUnit\":\"px\",\"style\":\"normal\",\"weight\":\"600\",\"lineHeight\":\"1\"},\"labelColor\":\"rgb(0, 0, 0)\",\"position\":\"left\",\"showTickLabels\":true,\"tickLabelFont\":{\"family\":\"Roboto\",\"size\":12,\"sizeUnit\":\"px\",\"style\":\"normal\",\"weight\":\"400\",\"lineHeight\":\"1\"},\"tickLabelColor\":\"rgba(0, 0, 0, 0.98)\",\"ticksFormatter\":null,\"showTicks\":true,\"ticksColor\":\"rgb(0, 0, 0)\",\"showLine\":true,\"lineColor\":\"rgba(0, 0, 0, 0.54)\",\"showSplitLines\":true,\"splitLinesColor\":\"rgba(0, 0, 0, 0.12)\",\"id\":\"default\",\"order\":0,\"ticksGenerator\":null,\"interval\":null,\"splitNumber\":null,\"min\":null,\"max\":null}},\"thresholds\":[],\"dataZoom\":true,\"stack\":false,\"grid\":{\"show\":true,\"backgroundColor\":\"#E5E7EB\",\"borderWidth\":1,\"borderColor\":\"#ccc\"},\"xAxis\":{\"show\":true,\"label\":\"\",\"labelFont\":{\"family\":\"Roboto\",\"size\":12,\"sizeUnit\":\"px\",\"style\":\"normal\",\"weight\":\"600\",\"lineHeight\":\"1\"},\"labelColor\":\"rgb(0, 0, 0)\",\"position\":\"bottom\",\"showTickLabels\":true,\"tickLabelFont\":{\"family\":\"Roboto\",\"size\":10,\"sizeUnit\":\"px\",\"style\":\"normal\",\"weight\":\"400\",\"lineHeight\":\"1\"},\"tickLabelColor\":\"rgb(0, 0, 0)\",\"ticksFormat\":{},\"showTicks\":true,\"ticksColor\":\"rgb(0, 0, 0)\",\"showLine\":true,\"lineColor\":\"rgba(0, 0, 0, 0.54)\",\"showSplitLines\":true,\"splitLinesColor\":\"rgba(0, 0, 0, 0.12)\"},\"noAggregationBarWidthSettings\":{\"strategy\":\"group\",\"groupWidth\":{\"relative\":true,\"relativeWidth\":2,\"absoluteWidth\":1000},\"barWidth\":{\"relative\":true,\"relativeWidth\":2,\"absoluteWidth\":1000}},\"showLegend\":true,\"legendColumnTitleFont\":{\"family\":\"Roboto\",\"size\":12,\"sizeUnit\":\"px\",\"style\":\"normal\",\"weight\":\"400\",\"lineHeight\":\"16px\"},\"legendColumnTitleColor\":\"rgb(0, 0, 0)\",\"legendLabelFont\":{\"family\":\"Roboto\",\"size\":12,\"sizeUnit\":\"px\",\"style\":\"normal\",\"weight\":\"400\",\"lineHeight\":\"16px\"},\"legendLabelColor\":\"rgb(0, 0, 0)\",\"legendValueFont\":{\"family\":\"Roboto\",\"size\":12,\"sizeUnit\":\"px\",\"style\":\"normal\",\"weight\":\"500\",\"lineHeight\":\"16px\"},\"legendValueColor\":\"rgb(0, 0, 0)\",\"legendConfig\":{\"direction\":\"column\",\"position\":\"top\",\"sortDataKeys\":false,\"showMin\":true,\"showMax\":true,\"showAvg\":true,\"showTotal\":false,\"showLatest\":false,\"valueFormat\":null},\"showTooltip\":true,\"tooltipTrigger\":\"axis\",\"tooltipLabelFont\":{\"family\":\"Roboto\",\"size\":12,\"sizeUnit\":\"px\",\"style\":\"normal\",\"weight\":\"400\",\"lineHeight\":\"16px\"},\"tooltipLabelColor\":\"rgb(0, 0, 0)\",\"tooltipValueFont\":{\"family\":\"Roboto\",\"size\":12,\"sizeUnit\":\"px\",\"style\":\"normal\",\"weight\":\"500\",\"lineHeight\":\"16px\"},\"tooltipValueColor\":\"rgb(0, 0, 0)\",\"tooltipValueFormatter\":null,\"tooltipShowDate\":true,\"tooltipDateFormat\":{\"format\":null,\"lastUpdateAgo\":false,\"custom\":false,\"auto\":true,\"autoDateFormatSettings\":{}},\"tooltipDateFont\":{\"family\":\"Roboto\",\"size\":11,\"sizeUnit\":\"px\",\"style\":\"normal\",\"weight\":\"400\",\"lineHeight\":\"16px\"},\"tooltipDateColor\":\"rgba(0, 0, 0, 0.76)\",\"tooltipDateInterval\":true,\"tooltipHideZeroValues\":null,\"tooltipBackgroundColor\":\"rgba(255, 255, 255, 0.76)\",\"tooltipBackgroundBlur\":4,\"animation\":{\"animation\":true,\"animationThreshold\":2000,\"animationDuration\":500,\"animationEasing\":\"cubicOut\",\"animationDelay\":0,\"animationDurationUpdate\":300,\"animationEasingUpdate\":\"cubicOut\",\"animationDelayUpdate\":0},\"background\":{\"type\":\"color\",\"color\":\"#fff\",\"overlay\":{\"enabled\":false,\"color\":\"rgba(255,255,255,0.72)\",\"blur\":3}},\"padding\":\"12px\"},\"title\":\"time series black 23\",\"dropShadow\":true,\"enableFullscreen\":true,\"titleStyle\":null,\"mobileHeight\":null,\"configMode\":\"advanced\",\"actions\":{},\"showTitleIcon\":false,\"titleIcon\":\"thermostat\",\"iconColor\":\"#1F6BDD\",\"useDashboardTimewindow\":false,\"displayTimewindow\":true,\"titleFont\":{\"size\":16,\"sizeUnit\":\"px\",\"family\":\"Roboto\",\"weight\":\"500\",\"style\":\"normal\",\"lineHeight\":\"24px\"},\"titleColor\":\"rgba(0, 0, 0, 0.87)\",\"titleTooltip\":\"\",\"widgetStyle\":{},\"widgetCss\":\"\",\"pageSize\":1024,\"units\":\"\",\"decimals\":null,\"noDataDisplayMessage\":\"\",\"timewindowStyle\":{\"showIcon\":false,\"iconSize\":\"24px\",\"icon\":null,\"iconPosition\":\"left\",\"font\":{\"size\":12,\"sizeUnit\":\"px\",\"family\":\"Roboto\",\"weight\":\"400\",\"style\":\"normal\",\"lineHeight\":\"16px\"},\"color\":\"rgba(0, 0, 0, 0.38)\",\"displayTypePrefix\":true},\"margin\":\"0px\",\"borderRadius\":\"0px\",\"iconSize\":\"0px\"}"
    },
    "externalId" : {
      "entityType" : "WIDGET_TYPE",
      "id" : "1b592720-ac64-11f0-a218-bb258a9774ff"
    },
    "resources" : null,
    "id" : {
      "entityType" : "WIDGET_TYPE",
      "id" : "1b592720-ac64-11f0-a218-bb258a9774ff"
    },
    "scada" : false,
    "tags" : [ "chart", "time series", "time-series", "line", "line chart", "bar", "bar chart", "point", "point chart" ]
  },
  "relations" : [ ],
  "attributes" : {
    "SERVER_SCOPE" : [ ]
  }
}